armodel/__init__.py
armodel/cli/__init__.py
armodel/cli/arxml_dump_cli.py
armodel/cli/arxml_format_cli.py
armodel/cli/connector2xlsx_cli.py
armodel/cli/connector_update_cli.py
armodel/cli/file_list_cli.py
armodel/cli/format_xml_cli.py
armodel/cli/memory_section_cli.py
armodel/cli/swc_list_cli.py
armodel/cli/system_signal_cli.py
armodel/cli/uuid_checker_cli.py
armodel/data_models/__init__.py
armodel/data_models/sw_connector.py
armodel/lib/__init__.py
armodel/lib/cli_args_parser.py
armodel/lib/sw_component.py
armodel/lib/system_signal.py
armodel/models/__init__.py
armodel/models/M2/__init__.py
armodel/models/M2/AUTOSARTemplates/AutosarTopLevelStructure.py
armodel/models/M2/AUTOSARTemplates/ECUCDescriptionTemplate.py
armodel/models/M2/AUTOSARTemplates/ECUCParameterDefTemplate.py
armodel/models/M2/AUTOSARTemplates/__init__.py
armodel/models/M2/AUTOSARTemplates/AdaptivePlatform/__init__.py
armodel/models/M2/AUTOSARTemplates/AdaptivePlatform/PlatformModuleDeployment/__init__.py
armodel/models/M2/AUTOSARTemplates/AdaptivePlatform/PlatformModuleDeployment/Firewall/FirewallRule.py
armodel/models/M2/AUTOSARTemplates/AdaptivePlatform/PlatformModuleDeployment/Firewall/FirewallRuleProps.py
armodel/models/M2/AUTOSARTemplates/AdaptivePlatform/PlatformModuleDeployment/Firewall/StateDependentFirewall.py
armodel/models/M2/AUTOSARTemplates/AdaptivePlatform/PlatformModuleDeployment/Firewall/__init__.py
armodel/models/M2/AUTOSARTemplates/AutosarTopLevelStructure/__init__.py
armodel/models/M2/AUTOSARTemplates/BswModuleTemplate/BswBehavior.py
armodel/models/M2/AUTOSARTemplates/BswModuleTemplate/BswImplementation.py
armodel/models/M2/AUTOSARTemplates/BswModuleTemplate/BswInterfaces.py
armodel/models/M2/AUTOSARTemplates/BswModuleTemplate/BswOverview.py
armodel/models/M2/AUTOSARTemplates/BswModuleTemplate/__init__.py
armodel/models/M2/AUTOSARTemplates/BswModuleTemplate/BswBehavior/BswAsynchronousServerCallReturnsEvent.py
armodel-1.9.1.dist-info/licenses/LICENSE
armodel-1.9.1.dist-info/METADATA
armodel-1.9.1.dist-info/WHEEL
armodel-1.9.1.dist-info/entry_points.txt
armodel-1.9.1.dist-info/top_level.txt
armodel-1.9.1.dist-info/RECORD
