Metadata-Version: 2.4
Name: armodel
Version: 1.9.1
Summary: the python arxml parser
Home-page: http://github.com/melodypapa/py-armodel
Author: melodypapa
Author-email: melodypapa <melodypapa@outlook.com>
License: MIT
Project-URL: Homepage, http://github.com/melodypapa/py-armodel
Keywords: AUTOSAR,ARXML
Classifier: Development Status :: 1 - Planning
Classifier: Environment :: Console
Classifier: Programming Language :: Python :: 3
Classifier: Operating System :: OS Independent
Requires-Python: >=3.5
License-File: LICENSE
Requires-Dist: colorama
Requires-Dist: openpyxl
Requires-Dist: lxml
Provides-Extra: pytest
Requires-Dist: pytest-cov; extra == "pytest"
Dynamic: author
Dynamic: home-page
Dynamic: license-file
Dynamic: requires-python
